dartmist/Mist.py
dartmist/MistHelpers.py
dartmist/MistWebsocket.py
dartmist/mist.py
dartmist/misthelpers.py
dartmist/mistwebsocket.py
dartmist-0.1.0.dist-info/COPYING
dartmist-0.1.0.dist-info/LICENSE
dartmist-0.1.0.dist-info/METADATA
dartmist-0.1.0.dist-info/WHEEL
dartmist-0.1.0.dist-info/top_level.txt
dartmist-0.1.0.dist-info/RECORD
