Metadata-Version: 2.1
Name: dartmist
Version: 0.1.0
Summary: A library for interacting with the Mist Systems API
Home-page: https://www.bryanward.net/dartmist
Author: Bryan Ward
Author-email: bryan@bryanward.net
License: UNKNOWN
Project-URL: Homepage, https://www.bryanward.net/dartmist
Project-URL: Source, https://github.com/bryanward-net/dartmist
Keywords: mist api wifi wi-fi juniper
Platform: UNKNOWN
Classifier: Programming Language :: Python :: 3
Classifier: License :: OSI Approved :: GNU General Public License v3 (GPLv3)
Classifier: Operating System :: OS Independent
Requires-Python: >=3.6
Requires-Dist: websocket
Requires-Dist: websocket-client
